tellter/TNS.py
tellter/__init__.py
tellter/safechat.py
tellter-0.0.12.dist-info/METADATA
tellter-0.0.12.dist-info/RECORD
tellter-0.0.12.dist-info/WHEEL
tellter-0.0.12.dist-info/top_level.txt
