Metadata-Version: 2.1
Name: tellter
Version: 0.0.12
Summary: Tellter Official Public API - Currently supports TNS and Safechat.
Home-page: https://tellter.com/
Author: Tellter
Author-email: contact@tellter.net
License: UNKNOWN
Platform: UNKNOWN
Classifier: Programming Language :: Python :: 3
Classifier: License :: OSI Approved :: MIT License
Classifier: Operating System :: OS Independent
